[{"pk": 1, "model": "humans.human", "fields": {"phaseA_npy": "numpy_abvs/hu011C57.npy", "updated": "2014-09-24 18:21:03.384686+00:00", "name": "hu011C57", "ethnicity": "WHITE,", "created": "2014-09-24 18:21:03.384686+00:00", "gender": "MALE", "index_in_big_file": 0, "age_range": 50, "chromosomal_sex": "UNKNOWN"}}, {"pk": 2, "model": "humans.human", "fields": {"phaseA_npy": "numpy_abvs/hu016B28.npy", "updated": "2014-09-24 18:21:03.384686+00:00", "name": "hu016B28", "ethnicity": "WHITE,", "created": "2014-09-24 18:21:03.384686+00:00", "gender": "MALE", "index_in_big_file": 1, "age_range": 40, "chromosomal_sex": "UNKNOWN"}}, {"pk": 3, "model": "humans.human", "fields": {"phaseA_npy": "numpy_abvs/hu0211D6.npy", "updated": "2014-09-24 18:21:03.384686+00:00", "name": "hu0211D6", "ethnicity": "WHITE,", "created": "2014-09-24 18:21:03.384686+00:00", "gender": "FEMALE", "index_in_big_file": 2, "age_range": 30, "chromosomal_sex": "UNKNOWN"}}, {"pk": 4, "model": "humans.human", "fields": {"phaseA_npy": "numpy_abvs/hu025CEA.npy", "updated": "2014-09-24 18:21:03.384686+00:00", "name": "hu025CEA", "ethnicity": "WHITE,", "created": "2014-09-24 18:21:03.384686+00:00", "gender": "FEMALE", "index_in_big_file": 3, "age_range": 40, "chromosomal_sex": "UNKNOWN"}}, {"pk": 5, "model": "humans.human", "fields": {"phaseA_npy": "numpy_abvs/hu032C04.npy", "updated": "2014-09-24 18:21:03.384686+00:00", "name": "hu032C04", "ethnicity": "WHITE,", "created": "2014-09-24 18:21:03.384686+00:00", "gender": "MALE", "index_in_big_file": 4, "age_range": 50, "chromosomal_sex": "UNKNOWN"}}, {"pk": 6, "model": "humans.human", "fields": {"phaseA_npy": "numpy_abvs/hu034DB1.npy", "updated": "2014-09-24 18:21:03.384686+00:00", "name": "hu034DB1", "ethnicity": "WHITE,", "created": "2014-09-24 18:21:03.384686+00:00", "gender": "FEMALE", "index_in_big_file": 5, "age_range": 50, "chromosomal_sex": "UNKNOWN"}}, {"pk": 7, "model": "humans.human", "fields": {"phaseA_npy": "numpy_abvs/hu040C0A.npy", "updated": "2014-09-24 18:21:03.384686+00:00", "name": "hu040C0A", "ethnicity": "WHITE,", "created": "2014-09-24 18:21:03.384686+00:00", "gender": "MALE", "index_in_big_file": 6, "age_range": 50, "chromosomal_sex": "UNKNOWN"}}, {"pk": 8, "model": "humans.human", "fields": {"phaseA_npy": "numpy_abvs/hu04DF3C.npy", "updated": "2014-09-24 18:21:03.384686+00:00", "name": "hu04DF3C", "ethnicity": "WHITE,", "created": "2014-09-24 18:21:03.384686+00:00", "gender": "FEMALE", "index_in_big_file": 7, "age_range": 50, "chromosomal_sex": "UNKNOWN"}}, {"pk": 9, "model": "humans.human", "fields": {"phaseA_npy": "numpy_abvs/hu04F220.npy", "updated": "2014-09-24 18:21:03.384686+00:00", "name": "hu04F220", "ethnicity": "UNKNOWN", "created": "2014-09-24 18:21:03.384686+00:00", "gender": "UNKNOWN", "index_in_big_file": 8, "age_range": -1, "chromosomal_sex": "UNKNOWN"}}, {"pk": 10, "model": "humans.human", "fields": {"phaseA_npy": "numpy_abvs/hu050E9C.npy", "updated": "2014-09-24 18:21:03.384686+00:00", "name": "hu050E9C", "ethnicity": "WHITE,", "created": "2014-09-24 18:21:03.384686+00:00", "gender": "MALE", "index_in_big_file": 9, "age_range": 70, "chromosomal_sex": "UNKNOWN"}}, {"pk": 11, "model": "humans.human", "fields": {"phaseA_npy": "numpy_abvs/hu05FD49.npy", "updated": "2014-09-24 18:21:03.384686+00:00", "name": "hu05FD49", "ethnicity": "WHITE,", "created": "2014-09-24 18:21:03.384686+00:00", "gender": "MALE", "index_in_big_file": 10, "age_range": 50, "chromosomal_sex": "UNKNOWN"}}, {"pk": 12, "model": "humans.human", "fields": {"phaseA_npy": "numpy_abvs/hu0A4518.npy", "updated": "2014-09-24 18:21:03.384686+00:00", "name": "hu0A4518", "ethnicity": "WHITE,", "created": "2014-09-24 18:21:03.384686+00:00", "gender": "MALE", "index_in_big_file": 11, "age_range": 20, "chromosomal_sex": "UNKNOWN"}}, {"pk": 13, "model": "humans.human", "fields": {"phaseA_npy": "numpy_abvs/hu0CF2EE.npy", "updated": "2014-09-24 18:21:03.384686+00:00", "name": "hu0CF2EE", "ethnicity": "AMER_INDIAN_ALASKAN,HAWAIIAN_PACIFIC_ISLAND,WHITE,", "created": "2014-09-24 18:21:03.384686+00:00", "gender": "MALE", "index_in_big_file": 12, "age_range": 30, "chromosomal_sex": "UNKNOWN"}}, {"pk": 14, "model": "humans.human", "fields": {"phaseA_npy": "numpy_abvs/hu0D1FA1.npy", "updated": "2014-09-24 18:21:03.384686+00:00", "name": "hu0D1FA1", "ethnicity": "WHITE,", "created": "2014-09-24 18:21:03.384686+00:00", "gender": "FEMALE", "index_in_big_file": 13, "age_range": 30, "chromosomal_sex": "UNKNOWN"}}, {"pk": 15, "model": "humans.human", "fields": {"phaseA_npy": "numpy_abvs/hu0D879F.npy", "updated": "2014-09-24 18:21:03.384686+00:00", "name": "hu0D879F", "ethnicity": "WHITE,", "created": "2014-09-24 18:21:03.384686+00:00", "gender": "MALE", "index_in_big_file": 14, "age_range": 60, "chromosomal_sex": "UNKNOWN"}}, {"pk": 16, "model": "humans.human", "fields": {"phaseA_npy": "numpy_abvs/hu0E64A1.npy", "updated": "2014-09-24 18:21:03.384686+00:00", "name": "hu0E64A1", "ethnicity": "WHITE,", "created": "2014-09-24 18:21:03.384686+00:00", "gender": "MALE", "index_in_big_file": 15, "age_range": 20, "chromosomal_sex": "UNKNOWN"}}, {"pk": 17, "model": "humans.human", "fields": {"phaseA_npy": "numpy_abvs/hu132B5C.npy", "updated": "2014-09-24 18:21:03.384686+00:00", "name": "hu132B5C", "ethnicity": "WHITE,", "created": "2014-09-24 18:21:03.384686+00:00", "gender": "FEMALE", "index_in_big_file": 16, "age_range": 30, "chromosomal_sex": "UNKNOWN"}}, {"pk": 18, "model": "humans.human", "fields": {"phaseA_npy": "numpy_abvs/hu1378E3.npy", "updated": "2014-09-24 18:21:03.384686+00:00", "name": "hu1378E3", "ethnicity": "UNKNOWN", "created": "2014-09-24 18:21:03.384686+00:00", "gender": "UNKNOWN", "index_in_big_file": 17, "age_range": -1, "chromosomal_sex": "UNKNOWN"}}, {"pk": 19, "model": "humans.human", "fields": {"phaseA_npy": "numpy_abvs/hu15FECA.npy", "updated": "2014-09-24 18:21:03.384686+00:00", "name": "hu15FECA", "ethnicity": "WHITE,", "created": "2014-09-24 18:21:03.384686+00:00", "gender": "MALE", "index_in_big_file": 18, "age_range": 30, "chromosomal_sex": "UNKNOWN"}}, {"pk": 20, "model": "humans.human", "fields": {"phaseA_npy": "numpy_abvs/hu1904EC.npy", "updated": "2014-09-24 18:21:03.384686+00:00", "name": "hu1904EC", "ethnicity": "WHITE,", "created": "2014-09-24 18:21:03.384686+00:00", "gender": "FEMALE", "index_in_big_file": 19, "age_range": 20, "chromosomal_sex": "UNKNOWN"}}, {"pk": 21, "model": "humans.human", "fields": {"phaseA_npy": "numpy_abvs/hu19C09F.npy", "updated": "2014-09-24 18:21:03.384686+00:00", "name": "hu19C09F", "ethnicity": "WHITE,", "created": "2014-09-24 18:21:03.384686+00:00", "gender": "MALE", "index_in_big_file": 20, "age_range": 40, "chromosomal_sex": "UNKNOWN"}}, {"pk": 22, "model": "humans.human", "fields": {"phaseA_npy": "numpy_abvs/hu1F73AB.npy", "updated": "2014-09-24 18:21:03.384686+00:00", "name": "hu1F73AB", "ethnicity": "WHITE,", "created": "2014-09-24 18:21:03.384686+00:00", "gender": "FEMALE", "index_in_big_file": 21, "age_range": 50, "chromosomal_sex": "UNKNOWN"}}, {"pk": 23, "model": "humans.human", "fields": {"phaseA_npy": "numpy_abvs/hu241DEA.npy", "updated": "2014-09-24 18:21:03.384686+00:00", "name": "hu241DEA", "ethnicity": "WHITE,", "created": "2014-09-24 18:21:03.384686+00:00", "gender": "MALE", "index_in_big_file": 22, "age_range": 40, "chromosomal_sex": "UNKNOWN"}}, {"pk": 24, "model": "humans.human", "fields": {"phaseA_npy": "numpy_abvs/hu24C863.npy", "updated": "2014-09-24 18:21:03.384686+00:00", "name": "hu24C863", "ethnicity": "WHITE,", "created": "2014-09-24 18:21:03.384686+00:00", "gender": "FEMALE", "index_in_big_file": 23, "age_range": 60, "chromosomal_sex": "UNKNOWN"}}, {"pk": 25, "model": "humans.human", "fields": {"phaseA_npy": "numpy_abvs/hu259AC7.npy", "updated": "2014-09-24 18:21:03.384686+00:00", "name": "hu259AC7", "ethnicity": "WHITE,", "created": "2014-09-24 18:21:03.384686+00:00", "gender": "MALE", "index_in_big_file": 24, "age_range": 20, "chromosomal_sex": "UNKNOWN"}}, {"pk": 26, "model": "humans.human", "fields": {"phaseA_npy": "numpy_abvs/hu26B551.npy", "updated": "2014-09-24 18:21:03.384686+00:00", "name": "hu26B551", "ethnicity": "WHITE,", "created": "2014-09-24 18:21:03.384686+00:00", "gender": "FEMALE", "index_in_big_file": 25, "age_range": 50, "chromosomal_sex": "UNKNOWN"}}, {"pk": 27, "model": "humans.human", "fields": {"phaseA_npy": "numpy_abvs/hu2843C9.npy", "updated": "2014-09-24 18:21:03.384686+00:00", "name": "hu2843C9", "ethnicity": "WHITE,", "created": "2014-09-24 18:21:03.384686+00:00", "gender": "MALE", "index_in_big_file": 26, "age_range": 70, "chromosomal_sex": "UNKNOWN"}}, {"pk": 28, "model": "humans.human", "fields": {"phaseA_npy": "numpy_abvs/hu297562.npy", "updated": "2014-09-24 18:21:03.384686+00:00", "name": "hu297562", "ethnicity": "WHITE,", "created": "2014-09-24 18:21:03.384686+00:00", "gender": "MALE", "index_in_big_file": 27, "age_range": 40, "chromosomal_sex": "UNKNOWN"}}, {"pk": 29, "model": "humans.human", "fields": {"phaseA_npy": "numpy_abvs/hu2C1D94.npy", "updated": "2014-09-24 18:21:03.384686+00:00", "name": "hu2C1D94", "ethnicity": "AMER_INDIAN_ALASKAN,WHITE,", "created": "2014-09-24 18:21:03.384686+00:00", "gender": "MALE", "index_in_big_file": 28, "age_range": 20, "chromosomal_sex": "UNKNOWN"}}, {"pk": 30, "model": "humans.human", "fields": {"phaseA_npy": "numpy_abvs/hu2D6140.npy", "updated": "2014-09-24 18:21:03.384686+00:00", "name": "hu2D6140", "ethnicity": "WHITE,", "created": "2014-09-24 18:21:03.384686+00:00", "gender": "FEMALE", "index_in_big_file": 29, "age_range": 70, "chromosomal_sex": "UNKNOWN"}}, {"pk": 31, "model": "humans.human", "fields": {"phaseA_npy": "numpy_abvs/hu2DBF2D.npy", "updated": "2014-09-24 18:21:03.384686+00:00", "name": "hu2DBF2D", "ethnicity": "WHITE,", "created": "2014-09-24 18:21:03.384686+00:00", "gender": "MALE", "index_in_big_file": 30, "age_range": 20, "chromosomal_sex": "UNKNOWN"}}, {"pk": 32, "model": "humans.human", "fields": {"phaseA_npy": "numpy_abvs/hu2FEC01.npy", "updated": "2014-09-24 18:21:03.384686+00:00", "name": "hu2FEC01", "ethnicity": "AMER_INDIAN_ALASKAN,WHITE,", "created": "2014-09-24 18:21:03.384686+00:00", "gender": "MALE", "index_in_big_file": 31, "age_range": 20, "chromosomal_sex": "UNKNOWN"}}, {"pk": 33, "model": "humans.human", "fields": {"phaseA_npy": "numpy_abvs/hu3073E3.npy", "updated": "2014-09-24 18:21:03.384686+00:00", "name": "hu3073E3", "ethnicity": "UNKNOWN", "created": "2014-09-24 18:21:03.384686+00:00", "gender": "UNKNOWN", "index_in_big_file": 32, "age_range": -1, "chromosomal_sex": "UNKNOWN"}}, {"pk": 34, "model": "humans.human", "fields": {"phaseA_npy": "numpy_abvs/hu33E2D9.npy", "updated": "2014-09-24 18:21:03.384686+00:00", "name": "hu33E2D9", "ethnicity": "WHITE,", "created": "2014-09-24 18:21:03.384686+00:00", "gender": "MALE", "index_in_big_file": 33, "age_range": 20, "chromosomal_sex": "UNKNOWN"}}, {"pk": 35, "model": "humans.human", "fields": {"phaseA_npy": "numpy_abvs/hu342A08.npy", "updated": "2014-09-24 18:21:03.384686+00:00", "name": "hu342A08", "ethnicity": "WHITE,", "created": "2014-09-24 18:21:03.384686+00:00", "gender": "FEMALE", "index_in_big_file": 34, "age_range": 60, "chromosomal_sex": "UNKNOWN"}}, {"pk": 36, "model": "humans.human", "fields": {"phaseA_npy": "numpy_abvs/hu34D5B9.npy", "updated": "2014-09-24 18:21:03.384686+00:00", "name": "hu34D5B9", "ethnicity": "WHITE,", "created": "2014-09-24 18:21:03.384686+00:00", "gender": "UNKNOWN", "index_in_big_file": 35, "age_range": 40, "chromosomal_sex": "UNKNOWN"}}, {"pk": 37, "model": "humans.human", "fields": {"phaseA_npy": "numpy_abvs/hu38168C.npy", "updated": "2014-09-24 18:21:03.384686+00:00", "name": "hu38168C", "ethnicity": "ASIAN,", "created": "2014-09-24 18:21:03.384686+00:00", "gender": "FEMALE", "index_in_big_file": 36, "age_range": 60, "chromosomal_sex": "UNKNOWN"}}, {"pk": 38, "model": "humans.human", "fields": {"phaseA_npy": "numpy_abvs/hu3A8D13.npy", "updated": "2014-09-24 18:21:03.384686+00:00", "name": "hu3A8D13", "ethnicity": "UNKNOWN", "created": "2014-09-24 18:21:03.384686+00:00", "gender": "UNKNOWN", "index_in_big_file": 37, "age_range": -1, "chromosomal_sex": "UNKNOWN"}}, {"pk": 39, "model": "humans.human", "fields": {"phaseA_npy": "numpy_abvs/hu3C0611.npy", "updated": "2014-09-24 18:21:03.384686+00:00", "name": "hu3C0611", "ethnicity": "WHITE,", "created": "2014-09-24 18:21:03.384686+00:00", "gender": "FEMALE", "index_in_big_file": 38, "age_range": 60, "chromosomal_sex": "UNKNOWN"}}, {"pk": 40, "model": "humans.human", "fields": {"phaseA_npy": "numpy_abvs/hu3CAB43.npy", "updated": "2014-09-24 18:21:03.384686+00:00", "name": "hu3CAB43", "ethnicity": "WHITE,", "created": "2014-09-24 18:21:03.384686+00:00", "gender": "MALE", "index_in_big_file": 39, "age_range": 40, "chromosomal_sex": "UNKNOWN"}}, {"pk": 41, "model": "humans.human", "fields": {"phaseA_npy": "numpy_abvs/hu3F864B.npy", "updated": "2014-09-24 18:21:03.384686+00:00", "name": "hu3F864B", "ethnicity": "HISPANIC_LATINO,", "created": "2014-09-24 18:21:03.384686+00:00", "gender": "FEMALE", "index_in_big_file": 40, "age_range": 50, "chromosomal_sex": "UNKNOWN"}}, {"pk": 42, "model": "humans.human", "fields": {"phaseA_npy": "numpy_abvs/hu4040B8.npy", "updated": "2014-09-24 18:21:03.384686+00:00", "name": "hu4040B8", "ethnicity": "WHITE,", "created": "2014-09-24 18:21:03.384686+00:00", "gender": "MALE", "index_in_big_file": 41, "age_range": 30, "chromosomal_sex": "UNKNOWN"}}, {"pk": 43, "model": "humans.human", "fields": {"phaseA_npy": "numpy_abvs/hu42D651.npy", "updated": "2014-09-24 18:21:03.384686+00:00", "name": "hu42D651", "ethnicity": "WHITE,", "created": "2014-09-24 18:21:03.384686+00:00", "gender": "MALE", "index_in_big_file": 42, "age_range": 30, "chromosomal_sex": "UNKNOWN"}}, {"pk": 44, "model": "humans.human", "fields": {"phaseA_npy": "numpy_abvs/hu432EB5.npy", "updated": "2014-09-24 18:21:03.384686+00:00", "name": "hu432EB5", "ethnicity": "WHITE,", "created": "2014-09-24 18:21:03.384686+00:00", "gender": "MALE", "index_in_big_file": 43, "age_range": 20, "chromosomal_sex": "UNKNOWN"}}, {"pk": 45, "model": "humans.human", "fields": {"phaseA_npy": "numpy_abvs/hu4339C0.npy", "updated": "2014-09-24 18:21:03.384686+00:00", "name": "hu4339C0", "ethnicity": "WHITE,", "created": "2014-09-24 18:21:03.384686+00:00", "gender": "MALE", "index_in_big_file": 44, "age_range": 70, "chromosomal_sex": "UNKNOWN"}}, {"pk": 46, "model": "humans.human", "fields": {"phaseA_npy": "numpy_abvs/hu448C4B.npy", "updated": "2014-09-24 18:21:03.384686+00:00", "name": "hu448C4B", "ethnicity": "WHITE,", "created": "2014-09-24 18:21:03.384686+00:00", "gender": "MALE", "index_in_big_file": 45, "age_range": 60, "chromosomal_sex": "UNKNOWN"}}, {"pk": 47, "model": "humans.human", "fields": {"phaseA_npy": "numpy_abvs/hu44DCFF.npy", "updated": "2014-09-24 18:21:03.384686+00:00", "name": "hu44DCFF", "ethnicity": "WHITE,", "created": "2014-09-24 18:21:03.384686+00:00", "gender": "MALE", "index_in_big_file": 46, "age_range": 20, "chromosomal_sex": "UNKNOWN"}}, {"pk": 48, "model": "humans.human", "fields": {"phaseA_npy": "numpy_abvs/hu470099.npy", "updated": "2014-09-24 18:21:03.384686+00:00", "name": "hu470099", "ethnicity": "AMER_INDIAN_ALASKAN,WHITE,", "created": "2014-09-24 18:21:03.384686+00:00", "gender": "MALE", "index_in_big_file": 47, "age_range": 40, "chromosomal_sex": "UNKNOWN"}}, {"pk": 49, "model": "humans.human", "fields": {"phaseA_npy": "numpy_abvs/hu48C4EB.npy", "updated": "2014-09-24 18:21:03.384686+00:00", "name": "hu48C4EB", "ethnicity": "WHITE,", "created": "2014-09-24 18:21:03.384686+00:00", "gender": "MALE", "index_in_big_file": 48, "age_range": 20, "chromosomal_sex": "UNKNOWN"}}, {"pk": 50, "model": "humans.human", "fields": {"phaseA_npy": "numpy_abvs/hu4B0812.npy", "updated": "2014-09-24 18:21:03.384686+00:00", "name": "hu4B0812", "ethnicity": "WHITE,", "created": "2014-09-24 18:21:03.384686+00:00", "gender": "MALE", "index_in_big_file": 49, "age_range": 40, "chromosomal_sex": "UNKNOWN"}}, {"pk": 51, "model": "humans.human", "fields": {"phaseA_npy": "numpy_abvs/hu4BE6F2.npy", "updated": "2014-09-24 18:21:03.384686+00:00", "name": "hu4BE6F2", "ethnicity": "WHITE,", "created": "2014-09-24 18:21:03.384686+00:00", "gender": "MALE", "index_in_big_file": 50, "age_range": 40, "chromosomal_sex": "UNKNOWN"}}, {"pk": 52, "model": "humans.human", "fields": {"phaseA_npy": "numpy_abvs/hu4BF398.npy", "updated": "2014-09-24 18:21:03.384686+00:00", "name": "hu4BF398", "ethnicity": "WHITE,", "created": "2014-09-24 18:21:03.384686+00:00", "gender": "MALE", "index_in_big_file": 51, "age_range": 60, "chromosomal_sex": "UNKNOWN"}}, {"pk": 53, "model": "humans.human", "fields": {"phaseA_npy": "numpy_abvs/hu4CA5B9.npy", "updated": "2014-09-24 18:21:03.384686+00:00", "name": "hu4CA5B9", "ethnicity": "WHITE,", "created": "2014-09-24 18:21:03.384686+00:00", "gender": "MALE", "index_in_big_file": 52, "age_range": 40, "chromosomal_sex": "UNKNOWN"}}, {"pk": 54, "model": "humans.human", "fields": {"phaseA_npy": "numpy_abvs/hu4FE0D1.npy", "updated": "2014-09-24 18:21:03.384686+00:00", "name": "hu4FE0D1", "ethnicity": "WHITE,", "created": "2014-09-24 18:21:03.384686+00:00", "gender": "MALE", "index_in_big_file": 53, "age_range": 30, "chromosomal_sex": "UNKNOWN"}}, {"pk": 55, "model": "humans.human", "fields": {"phaseA_npy": "numpy_abvs/hu52B7E5.npy", "updated": "2014-09-24 18:21:03.384686+00:00", "name": "hu52B7E5", "ethnicity": "WHITE,", "created": "2014-09-24 18:21:03.384686+00:00", "gender": "FEMALE", "index_in_big_file": 54, "age_range": 40, "chromosomal_sex": "UNKNOWN"}}, {"pk": 56, "model": "humans.human", "fields": {"phaseA_npy": "numpy_abvs/hu52F345.npy", "updated": "2014-09-24 18:21:03.384686+00:00", "name": "hu52F345", "ethnicity": "WHITE,", "created": "2014-09-24 18:21:03.384686+00:00", "gender": "FEMALE", "index_in_big_file": 55, "age_range": 30, "chromosomal_sex": "UNKNOWN"}}, {"pk": 57, "model": "humans.human", "fields": {"phaseA_npy": "numpy_abvs/hu553620.npy", "updated": "2014-09-24 18:21:03.384686+00:00", "name": "hu553620", "ethnicity": "WHITE,", "created": "2014-09-24 18:21:03.384686+00:00", "gender": "MALE", "index_in_big_file": 56, "age_range": 50, "chromosomal_sex": "UNKNOWN"}}, {"pk": 58, "model": "humans.human", "fields": {"phaseA_npy": "numpy_abvs/hu57A769.npy", "updated": "2014-09-24 18:21:03.384686+00:00", "name": "hu57A769", "ethnicity": "WHITE,", "created": "2014-09-24 18:21:03.384686+00:00", "gender": "MALE", "index_in_big_file": 57, "age_range": 30, "chromosomal_sex": "UNKNOWN"}}, {"pk": 59, "model": "humans.human", "fields": {"phaseA_npy": "numpy_abvs/hu589D0B.npy", "updated": "2014-09-24 18:21:03.384686+00:00", "name": "hu589D0B", "ethnicity": "WHITE,", "created": "2014-09-24 18:21:03.384686+00:00", "gender": "MALE", "index_in_big_file": 58, "age_range": 40, "chromosomal_sex": "UNKNOWN"}}, {"pk": 60, "model": "humans.human", "fields": {"phaseA_npy": "numpy_abvs/hu599905.npy", "updated": "2014-09-24 18:21:03.384686+00:00", "name": "hu599905", "ethnicity": "WHITE,", "created": "2014-09-24 18:21:03.384686+00:00", "gender": "MALE", "index_in_big_file": 59, "age_range": 50, "chromosomal_sex": "UNKNOWN"}}, {"pk": 61, "model": "humans.human", "fields": {"phaseA_npy": "numpy_abvs/hu5CD2C6.npy", "updated": "2014-09-24 18:21:03.384686+00:00", "name": "hu5CD2C6", "ethnicity": "WHITE,", "created": "2014-09-24 18:21:03.384686+00:00", "gender": "FEMALE", "index_in_big_file": 60, "age_range": 60, "chromosomal_sex": "UNKNOWN"}}, {"pk": 62, "model": "humans.human", "fields": {"phaseA_npy": "numpy_abvs/hu5FA322.npy", "updated": "2014-09-24 18:21:03.384686+00:00", "name": "hu5FA322", "ethnicity": "WHITE,", "created": "2014-09-24 18:21:03.384686+00:00", "gender": "FEMALE", "index_in_big_file": 61, "age_range": 70, "chromosomal_sex": "UNKNOWN"}}, {"pk": 63, "model": "humans.human", "fields": {"phaseA_npy": "numpy_abvs/hu5FB1B9.npy", "updated": "2014-09-24 18:21:03.384686+00:00", "name": "hu5FB1B9", "ethnicity": "UNKNOWN", "created": "2014-09-24 18:21:03.384686+00:00", "gender": "UNKNOWN", "index_in_big_file": 62, "age_range": -1, "chromosomal_sex": "UNKNOWN"}}, {"pk": 64, "model": "humans.human", "fields": {"phaseA_npy": "numpy_abvs/hu60180F.npy", "updated": "2014-09-24 18:21:03.384686+00:00", "name": "hu60180F", "ethnicity": "WHITE,", "created": "2014-09-24 18:21:03.384686+00:00", "gender": "FEMALE", "index_in_big_file": 63, "age_range": 60, "chromosomal_sex": "UNKNOWN"}}, {"pk": 65, "model": "humans.human", "fields": {"phaseA_npy": "numpy_abvs/hu60AB7C.npy", "updated": "2014-09-24 18:21:03.384686+00:00", "name": "hu60AB7C", "ethnicity": "WHITE,", "created": "2014-09-24 18:21:03.384686+00:00", "gender": "MALE", "index_in_big_file": 64, "age_range": 50, "chromosomal_sex": "UNKNOWN"}}, {"pk": 66, "model": "humans.human", "fields": {"phaseA_npy": "numpy_abvs/hu619F51.npy", "updated": "2014-09-24 18:21:03.384686+00:00", "name": "hu619F51", "ethnicity": "WHITE,", "created": "2014-09-24 18:21:03.384686+00:00", "gender": "MALE", "index_in_big_file": 65, "age_range": 30, "chromosomal_sex": "UNKNOWN"}}, {"pk": 67, "model": "humans.human", "fields": {"phaseA_npy": "numpy_abvs/hu627574.npy", "updated": "2014-09-24 18:21:03.384686+00:00", "name": "hu627574", "ethnicity": "WHITE,", "created": "2014-09-24 18:21:03.384686+00:00", "gender": "MALE", "index_in_big_file": 66, "age_range": 50, "chromosomal_sex": "UNKNOWN"}}, {"pk": 68, "model": "humans.human", "fields": {"phaseA_npy": "numpy_abvs/hu63EB0A.npy", "updated": "2014-09-24 18:21:03.384686+00:00", "name": "hu63EB0A", "ethnicity": "WHITE,", "created": "2014-09-24 18:21:03.384686+00:00", "gender": "MALE", "index_in_big_file": 67, "age_range": 40, "chromosomal_sex": "UNKNOWN"}}, {"pk": 69, "model": "humans.human", "fields": {"phaseA_npy": "numpy_abvs/hu64DBF7.npy", "updated": "2014-09-24 18:21:03.384686+00:00", "name": "hu64DBF7", "ethnicity": "WHITE,", "created": "2014-09-24 18:21:03.384686+00:00", "gender": "MALE", "index_in_big_file": 68, "age_range": 50, "chromosomal_sex": "UNKNOWN"}}, {"pk": 70, "model": "humans.human", "fields": {"phaseA_npy": "numpy_abvs/hu661AD0.npy", "updated": "2014-09-24 18:21:03.384686+00:00", "name": "hu661AD0", "ethnicity": "AMER_INDIAN_ALASKAN,HISPANIC_LATINO,BLACK_AA,WHITE,", "created": "2014-09-24 18:21:03.384686+00:00", "gender": "MALE", "index_in_big_file": 69, "age_range": 30, "chromosomal_sex": "UNKNOWN"}}, {"pk": 71, "model": "humans.human", "fields": {"phaseA_npy": "numpy_abvs/hu67EBB3.npy", "updated": "2014-09-24 18:21:03.384686+00:00", "name": "hu67EBB3", "ethnicity": "WHITE,", "created": "2014-09-24 18:21:03.384686+00:00", "gender": "FEMALE", "index_in_big_file": 70, "age_range": 20, "chromosomal_sex": "UNKNOWN"}}, {"pk": 72, "model": "humans.human", "fields": {"phaseA_npy": "numpy_abvs/hu687B6B.npy", "updated": "2014-09-24 18:21:03.384686+00:00", "name": "hu687B6B", "ethnicity": "WHITE,", "created": "2014-09-24 18:21:03.384686+00:00", "gender": "FEMALE", "index_in_big_file": 71, "age_range": 70, "chromosomal_sex": "UNKNOWN"}}, {"pk": 73, "model": "humans.human", "fields": {"phaseA_npy": "numpy_abvs/hu68929D.npy", "updated": "2014-09-24 18:21:03.384686+00:00", "name": "hu68929D", "ethnicity": "AMER_INDIAN_ALASKAN,WHITE,", "created": "2014-09-24 18:21:03.384686+00:00", "gender": "MALE", "index_in_big_file": 72, "age_range": 80, "chromosomal_sex": "UNKNOWN"}}, {"pk": 74, "model": "humans.human", "fields": {"phaseA_npy": "numpy_abvs/hu6C733E.npy", "updated": "2014-09-24 18:21:03.384686+00:00", "name": "hu6C733E", "ethnicity": "WHITE,", "created": "2014-09-24 18:21:03.384686+00:00", "gender": "MALE", "index_in_big_file": 73, "age_range": 20, "chromosomal_sex": "UNKNOWN"}}, {"pk": 75, "model": "humans.human", "fields": {"phaseA_npy": "numpy_abvs/hu6E4515.npy", "updated": "2014-09-24 18:21:03.384686+00:00", "name": "hu6E4515", "ethnicity": "WHITE,", "created": "2014-09-24 18:21:03.384686+00:00", "gender": "MALE", "index_in_big_file": 74, "age_range": 90, "chromosomal_sex": "UNKNOWN"}}, {"pk": 76, "model": "humans.human", "fields": {"phaseA_npy": "numpy_abvs/hu704A85.npy", "updated": "2014-09-24 18:21:03.384686+00:00", "name": "hu704A85", "ethnicity": "AMER_INDIAN_ALASKAN,HISPANIC_LATINO,WHITE,", "created": "2014-09-24 18:21:03.384686+00:00", "gender": "FEMALE", "index_in_big_file": 75, "age_range": 50, "chromosomal_sex": "UNKNOWN"}}, {"pk": 77, "model": "humans.human", "fields": {"phaseA_npy": "numpy_abvs/hu7123C1.npy", "updated": "2014-09-24 18:21:03.384686+00:00", "name": "hu7123C1", "ethnicity": "WHITE,", "created": "2014-09-24 18:21:03.384686+00:00", "gender": "MALE", "index_in_big_file": 76, "age_range": 60, "chromosomal_sex": "UNKNOWN"}}, {"pk": 78, "model": "humans.human", "fields": {"phaseA_npy": "numpy_abvs/hu71E59D.npy", "updated": "2014-09-24 18:21:03.384686+00:00", "name": "hu71E59D", "ethnicity": "WHITE,", "created": "2014-09-24 18:21:03.384686+00:00", "gender": "MALE", "index_in_big_file": 77, "age_range": 50, "chromosomal_sex": "UNKNOWN"}}, {"pk": 79, "model": "humans.human", "fields": {"phaseA_npy": "numpy_abvs/hu72A81D.npy", "updated": "2014-09-24 18:21:03.384686+00:00", "name": "hu72A81D", "ethnicity": "WHITE,", "created": "2014-09-24 18:21:03.384686+00:00", "gender": "FEMALE", "index_in_big_file": 78, "age_range": 40, "chromosomal_sex": "UNKNOWN"}}, {"pk": 80, "model": "humans.human", "fields": {"phaseA_npy": "numpy_abvs/hu72C17A.npy", "updated": "2014-09-24 18:21:03.384686+00:00", "name": "hu72C17A", "ethnicity": "WHITE,", "created": "2014-09-24 18:21:03.384686+00:00", "gender": "MALE", "index_in_big_file": 79, "age_range": 50, "chromosomal_sex": "UNKNOWN"}}, {"pk": 81, "model": "humans.human", "fields": {"phaseA_npy": "numpy_abvs/hu775356.npy", "updated": "2014-09-24 18:21:03.384686+00:00", "name": "hu775356", "ethnicity": "WHITE,", "created": "2014-09-24 18:21:03.384686+00:00", "gender": "MALE", "index_in_big_file": 80, "age_range": 50, "chromosomal_sex": "UNKNOWN"}}, {"pk": 82, "model": "humans.human", "fields": {"phaseA_npy": "numpy_abvs/hu7852C5.npy", "updated": "2014-09-24 18:21:03.384686+00:00", "name": "hu7852C5", "ethnicity": "WHITE,", "created": "2014-09-24 18:21:03.384686+00:00", "gender": "MALE", "index_in_big_file": 81, "age_range": 30, "chromosomal_sex": "UNKNOWN"}}, {"pk": 83, "model": "humans.human", "fields": {"phaseA_npy": "numpy_abvs/hu79F922.npy", "updated": "2014-09-24 18:21:03.384686+00:00", "name": "hu79F922", "ethnicity": "WHITE,", "created": "2014-09-24 18:21:03.384686+00:00", "gender": "MALE", "index_in_big_file": 82, "age_range": 60, "chromosomal_sex": "UNKNOWN"}}, {"pk": 84, "model": "humans.human", "fields": {"phaseA_npy": "numpy_abvs/hu7A2F1D.npy", "updated": "2014-09-24 18:21:03.384686+00:00", "name": "hu7A2F1D", "ethnicity": "WHITE,", "created": "2014-09-24 18:21:03.384686+00:00", "gender": "MALE", "index_in_big_file": 83, "age_range": 60, "chromosomal_sex": "UNKNOWN"}}, {"pk": 85, "model": "humans.human", "fields": {"phaseA_npy": "numpy_abvs/hu7A4AD1.npy", "updated": "2014-09-24 18:21:03.384686+00:00", "name": "hu7A4AD1", "ethnicity": "WHITE,", "created": "2014-09-24 18:21:03.384686+00:00", "gender": "FEMALE", "index_in_big_file": 84, "age_range": 30, "chromosomal_sex": "UNKNOWN"}}, {"pk": 86, "model": "humans.human", "fields": {"phaseA_npy": "numpy_abvs/hu7B594C.npy", "updated": "2014-09-24 18:21:03.384686+00:00", "name": "hu7B594C", "ethnicity": "WHITE,", "created": "2014-09-24 18:21:03.384686+00:00", "gender": "MALE", "index_in_big_file": 85, "age_range": 20, "chromosomal_sex": "UNKNOWN"}}, {"pk": 87, "model": "humans.human", "fields": {"phaseA_npy": "numpy_abvs/hu7DCBF9.npy", "updated": "2014-09-24 18:21:03.384686+00:00", "name": "hu7DCBF9", "ethnicity": "WHITE,", "created": "2014-09-24 18:21:03.384686+00:00", "gender": "MALE", "index_in_big_file": 86, "age_range": 30, "chromosomal_sex": "UNKNOWN"}}, {"pk": 88, "model": "humans.human", "fields": {"phaseA_npy": "numpy_abvs/hu8073B9.npy", "updated": "2014-09-24 18:21:03.384686+00:00", "name": "hu8073B9", "ethnicity": "WHITE,", "created": "2014-09-24 18:21:03.384686+00:00", "gender": "MALE", "index_in_big_file": 87, "age_range": 20, "chromosomal_sex": "UNKNOWN"}}, {"pk": 89, "model": "humans.human", "fields": {"phaseA_npy": "numpy_abvs/hu8229AE.npy", "updated": "2014-09-24 18:21:03.384686+00:00", "name": "hu8229AE", "ethnicity": "WHITE,", "created": "2014-09-24 18:21:03.384686+00:00", "gender": "FEMALE", "index_in_big_file": 88, "age_range": 40, "chromosomal_sex": "UNKNOWN"}}, {"pk": 90, "model": "humans.human", "fields": {"phaseA_npy": "numpy_abvs/hu82E689.npy", "updated": "2014-09-24 18:21:03.384686+00:00", "name": "hu82E689", "ethnicity": "WHITE,", "created": "2014-09-24 18:21:03.384686+00:00", "gender": "MALE", "index_in_big_file": 89, "age_range": 50, "chromosomal_sex": "UNKNOWN"}}, {"pk": 91, "model": "humans.human", "fields": {"phaseA_npy": "numpy_abvs/hu88A079.npy", "updated": "2014-09-24 18:21:03.384686+00:00", "name": "hu88A079", "ethnicity": "WHITE,", "created": "2014-09-24 18:21:03.384686+00:00", "gender": "MALE", "index_in_big_file": 90, "age_range": 60, "chromosomal_sex": "UNKNOWN"}}, {"pk": 92, "model": "humans.human", "fields": {"phaseA_npy": "numpy_abvs/hu8E2A35.npy", "updated": "2014-09-24 18:21:03.384686+00:00", "name": "hu8E2A35", "ethnicity": "WHITE,", "created": "2014-09-24 18:21:03.384686+00:00", "gender": "MALE", "index_in_big_file": 91, "age_range": 50, "chromosomal_sex": "UNKNOWN"}}, {"pk": 93, "model": "humans.human", "fields": {"phaseA_npy": "numpy_abvs/hu8E87A9.npy", "updated": "2014-09-24 18:21:03.384686+00:00", "name": "hu8E87A9", "ethnicity": "WHITE,", "created": "2014-09-24 18:21:03.384686+00:00", "gender": "FEMALE", "index_in_big_file": 92, "age_range": 70, "chromosomal_sex": "UNKNOWN"}}, {"pk": 94, "model": "humans.human", "fields": {"phaseA_npy": "numpy_abvs/hu8F918A.npy", "updated": "2014-09-24 18:21:03.384686+00:00", "name": "hu8F918A", "ethnicity": "WHITE,", "created": "2014-09-24 18:21:03.384686+00:00", "gender": "MALE", "index_in_big_file": 93, "age_range": 30, "chromosomal_sex": "UNKNOWN"}}, {"pk": 95, "model": "humans.human", "fields": {"phaseA_npy": "numpy_abvs/hu90B053.npy", "updated": "2014-09-24 18:21:03.384686+00:00", "name": "hu90B053", "ethnicity": "WHITE,", "created": "2014-09-24 18:21:03.384686+00:00", "gender": "FEMALE", "index_in_big_file": 94, "age_range": 40, "chromosomal_sex": "UNKNOWN"}}, {"pk": 96, "model": "humans.human", "fields": {"phaseA_npy": "numpy_abvs/hu92C40A.npy", "updated": "2014-09-24 18:21:03.384686+00:00", "name": "hu92C40A", "ethnicity": "AMER_INDIAN_ALASKAN,WHITE,", "created": "2014-09-24 18:21:03.384686+00:00", "gender": "FEMALE", "index_in_big_file": 95, "age_range": 60, "chromosomal_sex": "UNKNOWN"}}, {"pk": 97, "model": "humans.human", "fields": {"phaseA_npy": "numpy_abvs/hu92FD55.npy", "updated": "2014-09-24 18:21:03.384686+00:00", "name": "hu92FD55", "ethnicity": "ASIAN,", "created": "2014-09-24 18:21:03.384686+00:00", "gender": "MALE", "index_in_big_file": 96, "age_range": 20, "chromosomal_sex": "UNKNOWN"}}, {"pk": 98, "model": "humans.human", "fields": {"phaseA_npy": "numpy_abvs/hu939B7C.npy", "updated": "2014-09-24 18:21:03.384686+00:00", "name": "hu939B7C", "ethnicity": "WHITE,", "created": "2014-09-24 18:21:03.384686+00:00", "gender": "MALE", "index_in_big_file": 97, "age_range": 30, "chromosomal_sex": "UNKNOWN"}}, {"pk": 99, "model": "humans.human", "fields": {"phaseA_npy": "numpy_abvs/hu955EE1.npy", "updated": "2014-09-24 18:21:03.384686+00:00", "name": "hu955EE1", "ethnicity": "AMER_INDIAN_ALASKAN,WHITE,", "created": "2014-09-24 18:21:03.384686+00:00", "gender": "MALE", "index_in_big_file": 98, "age_range": 40, "chromosomal_sex": "UNKNOWN"}}, {"pk": 100, "model": "humans.human", "fields": {"phaseA_npy": "numpy_abvs/huA05317.npy", "updated": "2014-09-24 18:21:03.384686+00:00", "name": "huA05317", "ethnicity": "WHITE,", "created": "2014-09-24 18:21:03.384686+00:00", "gender": "MALE", "index_in_big_file": 99, "age_range": 50, "chromosomal_sex": "UNKNOWN"}}, {"pk": 101, "model": "humans.human", "fields": {"phaseA_npy": "numpy_abvs/huA0E089.npy", "updated": "2014-09-24 18:21:03.384686+00:00", "name": "huA0E089", "ethnicity": "WHITE,", "created": "2014-09-24 18:21:03.384686+00:00", "gender": "FEMALE", "index_in_big_file": 100, "age_range": 60, "chromosomal_sex": "UNKNOWN"}}, {"pk": 102, "model": "humans.human", "fields": {"phaseA_npy": "numpy_abvs/huA49E22.npy", "updated": "2014-09-24 18:21:03.384686+00:00", "name": "huA49E22", "ethnicity": "WHITE,", "created": "2014-09-24 18:21:03.384686+00:00", "gender": "MALE", "index_in_big_file": 101, "age_range": 40, "chromosomal_sex": "UNKNOWN"}}, {"pk": 103, "model": "humans.human", "fields": {"phaseA_npy": "numpy_abvs/huA4E2CF.npy", "updated": "2014-09-24 18:21:03.384686+00:00", "name": "huA4E2CF", "ethnicity": "WHITE,", "created": "2014-09-24 18:21:03.384686+00:00", "gender": "MALE", "index_in_big_file": 102, "age_range": 40, "chromosomal_sex": "UNKNOWN"}}, {"pk": 104, "model": "humans.human", "fields": {"phaseA_npy": "numpy_abvs/huA4F281.npy", "updated": "2014-09-24 18:21:03.384686+00:00", "name": "huA4F281", "ethnicity": "WHITE,", "created": "2014-09-24 18:21:03.384686+00:00", "gender": "MALE", "index_in_big_file": 103, "age_range": 30, "chromosomal_sex": "UNKNOWN"}}, {"pk": 105, "model": "humans.human", "fields": {"phaseA_npy": "numpy_abvs/huAE4A11.npy", "updated": "2014-09-24 18:21:03.384686+00:00", "name": "huAE4A11", "ethnicity": "ASIAN,WHITE,", "created": "2014-09-24 18:21:03.384686+00:00", "gender": "FEMALE", "index_in_big_file": 104, "age_range": 30, "chromosomal_sex": "UNKNOWN"}}, {"pk": 106, "model": "humans.human", "fields": {"phaseA_npy": "numpy_abvs/huAEADC0.npy", "updated": "2014-09-24 18:21:03.384686+00:00", "name": "huAEADC0", "ethnicity": "WHITE,", "created": "2014-09-24 18:21:03.384686+00:00", "gender": "MALE", "index_in_big_file": 105, "age_range": 50, "chromosomal_sex": "UNKNOWN"}}, {"pk": 107, "model": "humans.human", "fields": {"phaseA_npy": "numpy_abvs/huAEC1B0.npy", "updated": "2014-09-24 18:21:03.384686+00:00", "name": "huAEC1B0", "ethnicity": "WHITE,", "created": "2014-09-24 18:21:03.384686+00:00", "gender": "MALE", "index_in_big_file": 106, "age_range": 20, "chromosomal_sex": "UNKNOWN"}}, {"pk": 108, "model": "humans.human", "fields": {"phaseA_npy": "numpy_abvs/huAFA81C.npy", "updated": "2014-09-24 18:21:03.384686+00:00", "name": "huAFA81C", "ethnicity": "AMER_INDIAN_ALASKAN,WHITE,", "created": "2014-09-24 18:21:03.384686+00:00", "gender": "MALE", "index_in_big_file": 107, "age_range": 20, "chromosomal_sex": "UNKNOWN"}}, {"pk": 109, "model": "humans.human", "fields": {"phaseA_npy": "numpy_abvs/huB1FD55.npy", "updated": "2014-09-24 18:21:03.384686+00:00", "name": "huB1FD55", "ethnicity": "WHITE,", "created": "2014-09-24 18:21:03.384686+00:00", "gender": "MALE", "index_in_big_file": 108, "age_range": 50, "chromosomal_sex": "UNKNOWN"}}, {"pk": 110, "model": "humans.human", "fields": {"phaseA_npy": "numpy_abvs/huB4940E.npy", "updated": "2014-09-24 18:21:03.384686+00:00", "name": "huB4940E", "ethnicity": "WHITE,", "created": "2014-09-24 18:21:03.384686+00:00", "gender": "MALE", "index_in_big_file": 109, "age_range": 40, "chromosomal_sex": "UNKNOWN"}}, {"pk": 111, "model": "humans.human", "fields": {"phaseA_npy": "numpy_abvs/huB4D223.npy", "updated": "2014-09-24 18:21:03.384686+00:00", "name": "huB4D223", "ethnicity": "WHITE,", "created": "2014-09-24 18:21:03.384686+00:00", "gender": "MALE", "index_in_big_file": 110, "age_range": 20, "chromosomal_sex": "UNKNOWN"}}, {"pk": 112, "model": "humans.human", "fields": {"phaseA_npy": "numpy_abvs/huBA30D4.npy", "updated": "2014-09-24 18:21:03.384686+00:00", "name": "huBA30D4", "ethnicity": "WHITE,", "created": "2014-09-24 18:21:03.384686+00:00", "gender": "MALE", "index_in_big_file": 111, "age_range": 60, "chromosomal_sex": "UNKNOWN"}}, {"pk": 113, "model": "humans.human", "fields": {"phaseA_npy": "numpy_abvs/huBAAC98.npy", "updated": "2014-09-24 18:21:03.384686+00:00", "name": "huBAAC98", "ethnicity": "WHITE,", "created": "2014-09-24 18:21:03.384686+00:00", "gender": "MALE", "index_in_big_file": 112, "age_range": 30, "chromosomal_sex": "UNKNOWN"}}, {"pk": 114, "model": "humans.human", "fields": {"phaseA_npy": "numpy_abvs/huBE0B25.npy", "updated": "2014-09-24 18:21:03.384686+00:00", "name": "huBE0B25", "ethnicity": "WHITE,", "created": "2014-09-24 18:21:03.384686+00:00", "gender": "MALE", "index_in_big_file": 113, "age_range": 30, "chromosomal_sex": "UNKNOWN"}}, {"pk": 115, "model": "humans.human", "fields": {"phaseA_npy": "numpy_abvs/huBEDA0B.npy", "updated": "2014-09-24 18:21:03.384686+00:00", "name": "huBEDA0B", "ethnicity": "WHITE,", "created": "2014-09-24 18:21:03.384686+00:00", "gender": "FEMALE", "index_in_big_file": 114, "age_range": 60, "chromosomal_sex": "UNKNOWN"}}, {"pk": 116, "model": "humans.human", "fields": {"phaseA_npy": "numpy_abvs/huC14AE1.npy", "updated": "2014-09-24 18:21:03.384686+00:00", "name": "huC14AE1", "ethnicity": "WHITE,", "created": "2014-09-24 18:21:03.384686+00:00", "gender": "MALE", "index_in_big_file": 115, "age_range": 20, "chromosomal_sex": "UNKNOWN"}}, {"pk": 117, "model": "humans.human", "fields": {"phaseA_npy": "numpy_abvs/huC29627.npy", "updated": "2014-09-24 18:21:03.384686+00:00", "name": "huC29627", "ethnicity": "WHITE,", "created": "2014-09-24 18:21:03.384686+00:00", "gender": "MALE", "index_in_big_file": 116, "age_range": 20, "chromosomal_sex": "UNKNOWN"}}, {"pk": 118, "model": "humans.human", "fields": {"phaseA_npy": "numpy_abvs/huC3160A.npy", "updated": "2014-09-24 18:21:03.384686+00:00", "name": "huC3160A", "ethnicity": "WHITE,", "created": "2014-09-24 18:21:03.384686+00:00", "gender": "MALE", "index_in_big_file": 117, "age_range": 50, "chromosomal_sex": "UNKNOWN"}}, {"pk": 119, "model": "humans.human", "fields": {"phaseA_npy": "numpy_abvs/huC434ED.npy", "updated": "2014-09-24 18:21:03.384686+00:00", "name": "huC434ED", "ethnicity": "WHITE,", "created": "2014-09-24 18:21:03.384686+00:00", "gender": "MALE", "index_in_big_file": 118, "age_range": 20, "chromosomal_sex": "UNKNOWN"}}, {"pk": 120, "model": "humans.human", "fields": {"phaseA_npy": "numpy_abvs/huC5733C.npy", "updated": "2014-09-24 18:21:03.384686+00:00", "name": "huC5733C", "ethnicity": "WHITE,", "created": "2014-09-24 18:21:03.384686+00:00", "gender": "MALE", "index_in_big_file": 119, "age_range": 50, "chromosomal_sex": "UNKNOWN"}}, {"pk": 121, "model": "humans.human", "fields": {"phaseA_npy": "numpy_abvs/huC92BC9.npy", "updated": "2014-09-24 18:21:03.384686+00:00", "name": "huC92BC9", "ethnicity": "WHITE,", "created": "2014-09-24 18:21:03.384686+00:00", "gender": "FEMALE", "index_in_big_file": 120, "age_range": 20, "chromosomal_sex": "UNKNOWN"}}, {"pk": 122, "model": "humans.human", "fields": {"phaseA_npy": "numpy_abvs/huC93106.npy", "updated": "2014-09-24 18:21:03.384686+00:00", "name": "huC93106", "ethnicity": "WHITE,", "created": "2014-09-24 18:21:03.384686+00:00", "gender": "FEMALE", "index_in_big_file": 121, "age_range": 50, "chromosomal_sex": "UNKNOWN"}}, {"pk": 123, "model": "humans.human", "fields": {"phaseA_npy": "numpy_abvs/huCA017E.npy", "updated": "2014-09-24 18:21:03.384686+00:00", "name": "huCA017E", "ethnicity": "ASIAN,", "created": "2014-09-24 18:21:03.384686+00:00", "gender": "MALE", "index_in_big_file": 122, "age_range": 60, "chromosomal_sex": "UNKNOWN"}}, {"pk": 124, "model": "humans.human", "fields": {"phaseA_npy": "numpy_abvs/huCA14D2.npy", "updated": "2014-09-24 18:21:03.384686+00:00", "name": "huCA14D2", "ethnicity": "WHITE,", "created": "2014-09-24 18:21:03.384686+00:00", "gender": "FEMALE", "index_in_big_file": 123, "age_range": 50, "chromosomal_sex": "UNKNOWN"}}, {"pk": 125, "model": "humans.human", "fields": {"phaseA_npy": "numpy_abvs/huCCAFD0.npy", "updated": "2014-09-24 18:21:03.384686+00:00", "name": "huCCAFD0", "ethnicity": "WHITE,", "created": "2014-09-24 18:21:03.384686+00:00", "gender": "MALE", "index_in_big_file": 124, "age_range": 70, "chromosomal_sex": "UNKNOWN"}}, {"pk": 126, "model": "humans.human", "fields": {"phaseA_npy": "numpy_abvs/huCD380F.npy", "updated": "2014-09-24 18:21:03.384686+00:00", "name": "huCD380F", "ethnicity": "WHITE,", "created": "2014-09-24 18:21:03.384686+00:00", "gender": "FEMALE", "index_in_big_file": 125, "age_range": 20, "chromosomal_sex": "UNKNOWN"}}, {"pk": 127, "model": "humans.human", "fields": {"phaseA_npy": "numpy_abvs/huD09534.npy", "updated": "2014-09-24 18:21:03.384686+00:00", "name": "huD09534", "ethnicity": "WHITE,", "created": "2014-09-24 18:21:03.384686+00:00", "gender": "FEMALE", "index_in_big_file": 126, "age_range": 30, "chromosomal_sex": "UNKNOWN"}}, {"pk": 128, "model": "humans.human", "fields": {"phaseA_npy": "numpy_abvs/huD103CC.npy", "updated": "2014-09-24 18:21:03.384686+00:00", "name": "huD103CC", "ethnicity": "UNKNOWN", "created": "2014-09-24 18:21:03.384686+00:00", "gender": "UNKNOWN", "index_in_big_file": 127, "age_range": -1, "chromosomal_sex": "UNKNOWN"}}, {"pk": 129, "model": "humans.human", "fields": {"phaseA_npy": "numpy_abvs/huD10E53.npy", "updated": "2014-09-24 18:21:03.384686+00:00", "name": "huD10E53", "ethnicity": "WHITE,", "created": "2014-09-24 18:21:03.384686+00:00", "gender": "MALE", "index_in_big_file": 128, "age_range": 30, "chromosomal_sex": "UNKNOWN"}}, {"pk": 130, "model": "humans.human", "fields": {"phaseA_npy": "numpy_abvs/huD37D14.npy", "updated": "2014-09-24 18:21:03.384686+00:00", "name": "huD37D14", "ethnicity": "WHITE,", "created": "2014-09-24 18:21:03.384686+00:00", "gender": "FEMALE", "index_in_big_file": 129, "age_range": 40, "chromosomal_sex": "UNKNOWN"}}, {"pk": 131, "model": "humans.human", "fields": {"phaseA_npy": "numpy_abvs/huD52556.npy", "updated": "2014-09-24 18:21:03.384686+00:00", "name": "huD52556", "ethnicity": "WHITE,", "created": "2014-09-24 18:21:03.384686+00:00", "gender": "MALE", "index_in_big_file": 130, "age_range": 40, "chromosomal_sex": "UNKNOWN"}}, {"pk": 132, "model": "humans.human", "fields": {"phaseA_npy": "numpy_abvs/huD81F3D.npy", "updated": "2014-09-24 18:21:03.384686+00:00", "name": "huD81F3D", "ethnicity": "WHITE,", "created": "2014-09-24 18:21:03.384686+00:00", "gender": "MALE", "index_in_big_file": 131, "age_range": 40, "chromosomal_sex": "UNKNOWN"}}, {"pk": 133, "model": "humans.human", "fields": {"phaseA_npy": "numpy_abvs/huD9EE1E.npy", "updated": "2014-09-24 18:21:03.384686+00:00", "name": "huD9EE1E", "ethnicity": "UNKNOWN", "created": "2014-09-24 18:21:03.384686+00:00", "gender": "UNKNOWN", "index_in_big_file": 132, "age_range": -1, "chromosomal_sex": "UNKNOWN"}}, {"pk": 134, "model": "humans.human", "fields": {"phaseA_npy": "numpy_abvs/huDBD591.npy", "updated": "2014-09-24 18:21:03.384686+00:00", "name": "huDBD591", "ethnicity": "WHITE,", "created": "2014-09-24 18:21:03.384686+00:00", "gender": "MALE", "index_in_big_file": 133, "age_range": 20, "chromosomal_sex": "UNKNOWN"}}, {"pk": 135, "model": "humans.human", "fields": {"phaseA_npy": "numpy_abvs/huDBF9DD.npy", "updated": "2014-09-24 18:21:03.384686+00:00", "name": "huDBF9DD", "ethnicity": "WHITE,", "created": "2014-09-24 18:21:03.384686+00:00", "gender": "MALE", "index_in_big_file": 134, "age_range": 40, "chromosomal_sex": "UNKNOWN"}}, {"pk": 136, "model": "humans.human", "fields": {"phaseA_npy": "numpy_abvs/huDE435D.npy", "updated": "2014-09-24 18:21:03.384686+00:00", "name": "huDE435D", "ethnicity": "WHITE,", "created": "2014-09-24 18:21:03.384686+00:00", "gender": "MALE", "index_in_big_file": 135, "age_range": 50, "chromosomal_sex": "UNKNOWN"}}, {"pk": 137, "model": "humans.human", "fields": {"phaseA_npy": "numpy_abvs/huDF04CC.npy", "updated": "2014-09-24 18:21:03.384686+00:00", "name": "huDF04CC", "ethnicity": "WHITE,", "created": "2014-09-24 18:21:03.384686+00:00", "gender": "FEMALE", "index_in_big_file": 136, "age_range": 60, "chromosomal_sex": "UNKNOWN"}}, {"pk": 138, "model": "humans.human", "fields": {"phaseA_npy": "numpy_abvs/huE58004.npy", "updated": "2014-09-24 18:21:03.384686+00:00", "name": "huE58004", "ethnicity": "WHITE,", "created": "2014-09-24 18:21:03.384686+00:00", "gender": "FEMALE", "index_in_big_file": 137, "age_range": 30, "chromosomal_sex": "UNKNOWN"}}, {"pk": 139, "model": "humans.human", "fields": {"phaseA_npy": "numpy_abvs/huE9B698.npy", "updated": "2014-09-24 18:21:03.384686+00:00", "name": "huE9B698", "ethnicity": "WHITE,", "created": "2014-09-24 18:21:03.384686+00:00", "gender": "MALE", "index_in_big_file": 138, "age_range": 30, "chromosomal_sex": "UNKNOWN"}}, {"pk": 140, "model": "humans.human", "fields": {"phaseA_npy": "numpy_abvs/huEA4EE5.npy", "updated": "2014-09-24 18:21:03.384686+00:00", "name": "huEA4EE5", "ethnicity": "HISPANIC_LATINO,", "created": "2014-09-24 18:21:03.384686+00:00", "gender": "MALE", "index_in_big_file": 139, "age_range": 40, "chromosomal_sex": "UNKNOWN"}}, {"pk": 141, "model": "humans.human", "fields": {"phaseA_npy": "numpy_abvs/huEBD467.npy", "updated": "2014-09-24 18:21:03.384686+00:00", "name": "huEBD467", "ethnicity": "WHITE,", "created": "2014-09-24 18:21:03.384686+00:00", "gender": "MALE", "index_in_big_file": 140, "age_range": 30, "chromosomal_sex": "UNKNOWN"}}, {"pk": 142, "model": "humans.human", "fields": {"phaseA_npy": "numpy_abvs/huEC6EEC.npy", "updated": "2014-09-24 18:21:03.384686+00:00", "name": "huEC6EEC", "ethnicity": "HISPANIC_LATINO,WHITE,", "created": "2014-09-24 18:21:03.384686+00:00", "gender": "FEMALE", "index_in_big_file": 141, "age_range": 40, "chromosomal_sex": "UNKNOWN"}}, {"pk": 143, "model": "humans.human", "fields": {"phaseA_npy": "numpy_abvs/huED0F40.npy", "updated": "2014-09-24 18:21:03.384686+00:00", "name": "huED0F40", "ethnicity": "WHITE,", "created": "2014-09-24 18:21:03.384686+00:00", "gender": "MALE", "index_in_big_file": 142, "age_range": 40, "chromosomal_sex": "UNKNOWN"}}, {"pk": 144, "model": "humans.human", "fields": {"phaseA_npy": "numpy_abvs/huEDEA65.npy", "updated": "2014-09-24 18:21:03.384686+00:00", "name": "huEDEA65", "ethnicity": "WHITE,", "created": "2014-09-24 18:21:03.384686+00:00", "gender": "MALE", "index_in_big_file": 143, "age_range": 20, "chromosomal_sex": "UNKNOWN"}}, {"pk": 145, "model": "humans.human", "fields": {"phaseA_npy": "numpy_abvs/huEDF7DA.npy", "updated": "2014-09-24 18:21:03.384686+00:00", "name": "huEDF7DA", "ethnicity": "WHITE,", "created": "2014-09-24 18:21:03.384686+00:00", "gender": "FEMALE", "index_in_big_file": 144, "age_range": 50, "chromosomal_sex": "UNKNOWN"}}, {"pk": 146, "model": "humans.human", "fields": {"phaseA_npy": "numpy_abvs/huF1DC30.npy", "updated": "2014-09-24 18:21:03.384686+00:00", "name": "huF1DC30", "ethnicity": "WHITE,", "created": "2014-09-24 18:21:03.384686+00:00", "gender": "MALE", "index_in_big_file": 145, "age_range": 40, "chromosomal_sex": "UNKNOWN"}}, {"pk": 147, "model": "humans.human", "fields": {"phaseA_npy": "numpy_abvs/huF5AD12.npy", "updated": "2014-09-24 18:21:03.384686+00:00", "name": "huF5AD12", "ethnicity": "WHITE,", "created": "2014-09-24 18:21:03.384686+00:00", "gender": "MALE", "index_in_big_file": 146, "age_range": 30, "chromosomal_sex": "UNKNOWN"}}, {"pk": 148, "model": "humans.human", "fields": {"phaseA_npy": "numpy_abvs/huF5E0B6.npy", "updated": "2014-09-24 18:21:03.384686+00:00", "name": "huF5E0B6", "ethnicity": "WHITE,", "created": "2014-09-24 18:21:03.384686+00:00", "gender": "MALE", "index_in_big_file": 147, "age_range": 30, "chromosomal_sex": "UNKNOWN"}}, {"pk": 149, "model": "humans.human", "fields": {"phaseA_npy": "numpy_abvs/huF80F84.npy", "updated": "2014-09-24 18:21:03.384686+00:00", "name": "huF80F84", "ethnicity": "WHITE,", "created": "2014-09-24 18:21:03.384686+00:00", "gender": "FEMALE", "index_in_big_file": 148, "age_range": 20, "chromosomal_sex": "UNKNOWN"}}, {"pk": 150, "model": "humans.human", "fields": {"phaseA_npy": "numpy_abvs/huFA70A3.npy", "updated": "2014-09-24 18:21:03.384686+00:00", "name": "huFA70A3", "ethnicity": "WHITE,", "created": "2014-09-24 18:21:03.384686+00:00", "gender": "MALE", "index_in_big_file": 149, "age_range": 40, "chromosomal_sex": "UNKNOWN"}}, {"pk": 151, "model": "humans.human", "fields": {"phaseA_npy": "numpy_abvs/huFAF983.npy", "updated": "2014-09-24 18:21:03.384686+00:00", "name": "huFAF983", "ethnicity": "WHITE,", "created": "2014-09-24 18:21:03.384686+00:00", "gender": "MALE", "index_in_big_file": 150, "age_range": 50, "chromosomal_sex": "UNKNOWN"}}, {"pk": 152, "model": "humans.human", "fields": {"phaseA_npy": "numpy_abvs/huFE71F3.npy", "updated": "2014-09-24 18:21:03.384686+00:00", "name": "huFE71F3", "ethnicity": "WHITE,", "created": "2014-09-24 18:21:03.384686+00:00", "gender": "MALE", "index_in_big_file": 151, "age_range": 50, "chromosomal_sex": "UNKNOWN"}}, {"pk": 153, "model": "humans.human", "fields": {"phaseA_npy": "numpy_abvs/huFFAD87.npy", "updated": "2014-09-24 18:21:03.384686+00:00", "name": "huFFAD87", "ethnicity": "WHITE,", "created": "2014-09-24 18:21:03.384686+00:00", "gender": "MALE", "index_in_big_file": 152, "age_range": 30, "chromosomal_sex": "UNKNOWN"}}, {"pk": 154, "model": "humans.human", "fields": {"phaseA_npy": "numpy_abvs/huFFB09D.npy", "updated": "2014-09-24 18:21:03.384686+00:00", "name": "huFFB09D", "ethnicity": "WHITE,", "created": "2014-09-24 18:21:03.384686+00:00", "gender": "FEMALE", "index_in_big_file": 153, "age_range": 40, "chromosomal_sex": "UNKNOWN"}}]